xyz_school/__init__.py
xyz_school/admin.py
xyz_school/apis.py
xyz_school/apps.py
xyz_school/choices.py
xyz_school/helper.py
xyz_school/importers.py
xyz_school/models.py
xyz_school/receivers.py
xyz_school/serializers.py
xyz_school/stats.py
xyz_school/tasks.py
xyz_school/validators.py
xyz_school/migrations/0001_initial.py
xyz_school/migrations/0002_teacher_description.py
xyz_school/migrations/0003_student_is_formal.py
xyz_school/migrations/0004_class_major.py
xyz_school/migrations/0005_major_courses.py
xyz_school/migrations/0006_class_tags.py
xyz_school/migrations/0007_auto_20211212_1954.py
xyz_school/migrations/0008_auto_20220112_0807.py
xyz_school/migrations/0009_auto_20220120_0006.py
xyz_school/migrations/0010_auto_20230219_2347.py
xyz_school/migrations/0011_classcourse_is_active.py
xyz_school/migrations/__init__.py
xyz_school-0.3.0.dist-info/METADATA
xyz_school-0.3.0.dist-info/WHEEL
xyz_school-0.3.0.dist-info/top_level.txt
xyz_school-0.3.0.dist-info/RECORD
